dimibob/__init__.py
dimibob-1.0.0.dist-info/DESCRIPTION.rst
dimibob-1.0.0.dist-info/METADATA
dimibob-1.0.0.dist-info/RECORD
dimibob-1.0.0.dist-info/WHEEL
dimibob-1.0.0.dist-info/metadata.json
dimibob-1.0.0.dist-info/top_level.txt
