Metadata-Version: 2.0
Name: dimibob
Version: 1.0.0
Summary: Korea Digital Media Highschool meal data crawler
Home-page: https://github.com/ChalkPE/dimibob-py
Author: ChalkPE
Author-email: chalk@chalk.pe
License: MIT
Platform: UNKNOWN
Requires-Python: >=3
Requires-Dist: bs4
Requires-Dist: requests
